MathFunc/__init__.py
MathFunc-0.1.5.dist-info/DESCRIPTION.rst
MathFunc-0.1.5.dist-info/METADATA
MathFunc-0.1.5.dist-info/metadata.json
MathFunc-0.1.5.dist-info/RECORD
MathFunc-0.1.5.dist-info/top_level.txt
MathFunc-0.1.5.dist-info/WHEEL
