Metadata-Version: 2.0
Name: MathFunc
Version: 0.1.5
Summary: Python Function with Conditions and Scope
Home-page: http://github.com/MBALearnsToCode/PyMathFunc
Author: Vinh Luong (a.k.a. MBALearnsToCode)
Author-email: MBALearnsToCode@UChicago.edu
License: MIT License
Keywords: math func function conditions scope
Platform: UNKNOWN
Requires-Dist: CompyledFunc
Requires-Dist: FrozenDict
Requires-Dist: HelpyFuncs
Requires-Dist: MathDict
Requires-Dist: SymPy
